cleverslice/__init__.py
cleverslice/sdict.py
src/slicedict/__init__.py
cleverslice-1.0.1.dist-info/LICENSE
cleverslice-1.0.1.dist-info/METADATA
cleverslice-1.0.1.dist-info/WHEEL
cleverslice-1.0.1.dist-info/top_level.txt
cleverslice-1.0.1.dist-info/RECORD
