Metadata-Version: 2.1
Name: cleverslice
Version: 1.0.1
Summary: Slice dictionaries just like tuples and lists
Author-email: Gu waakzi <guwaakzi@gmail.com>
Project-URL: url, https://github.com/Guwaakzi/cleverslice
Classifier: License :: OSI Approved :: MIT License
Classifier: Programming Language :: Python :: 3.8
Classifier: Programming Language :: Python :: 3.9
Classifier: Programming Language :: Python :: 3.10
Classifier: Programming Language :: Python :: 3.11
Classifier: Operating System :: OS Independent
Requires-Python: >=3.8
License-File: LICENSE
